RenewableGANBackend/__init__.py
RenewableGANBackend/backend.py
RenewableGANBackend/config.py
RenewableGANBackend/gan_utils.py
RenewableGANBackend/generate_solar_wind_gan.py
chronix2grid/GeneratorBackend.py
chronix2grid/__init__.py
chronix2grid/config.py
chronix2grid/constants.py
chronix2grid/default_backend.py
chronix2grid/main.py
chronix2grid/output_processor.py
chronix2grid/seed_manager.py
chronix2grid/utils.py
chronix2grid/generation/__init__.py
chronix2grid/generation/generate_chronics.py
chronix2grid/generation/generation_utils.py
chronix2grid/generation/_dispatch/__init__.py
chronix2grid/generation/_dispatch/_PypsaDispatchBackend/PypsaEconomicDispatch.py
chronix2grid/generation/_dispatch/_PypsaDispatchBackend/__init__.py
chronix2grid/generation/_dispatch/_PypsaDispatchBackend/_EDispatch_L2RPN2020/__init__.py
chronix2grid/generation/_dispatch/_PypsaDispatchBackend/_EDispatch_L2RPN2020/run_economic_dispatch.py
chronix2grid/generation/_dispatch/_PypsaDispatchBackend/_EDispatch_L2RPN2020/utils.py
chronix2grid/generation/consumption/ConsumptionGeneratorBackend.py
chronix2grid/generation/consumption/__init__.py
chronix2grid/generation/consumption/consumption_utils.py
chronix2grid/generation/consumption/generate_load.py
chronix2grid/generation/dispatch/DispatchBackend.py
chronix2grid/generation/dispatch/EconomicDispatch.py
chronix2grid/generation/dispatch/__init__.py
chronix2grid/generation/dispatch/dispatch_loss_utils.py
chronix2grid/generation/dispatch/generate_dispatch.py
chronix2grid/generation/dispatch/utils.py
chronix2grid/generation/dispatch/PypsaDispatchBackend/__init__.py
chronix2grid/generation/dispatch/PypsaDispatchBackend/EDispatch_L2RPN2020/__init__.py
chronix2grid/generation/hydro/__init__.py
chronix2grid/generation/hydro/make_hydro_guide_curves.py
chronix2grid/generation/loss/LossBackend.py
chronix2grid/generation/loss/__init__.py
chronix2grid/generation/loss/generate_loss.py
chronix2grid/generation/renewable/RenewableBackend.py
Chronix2Grid-1.2.0.post1.dist-info/AUTHORS.txt
Chronix2Grid-1.2.0.post1.dist-info/LICENSE
Chronix2Grid-1.2.0.post1.dist-info/METADATA
Chronix2Grid-1.2.0.post1.dist-info/WHEEL
Chronix2Grid-1.2.0.post1.dist-info/entry_points.txt
Chronix2Grid-1.2.0.post1.dist-info/top_level.txt
Chronix2Grid-1.2.0.post1.dist-info/RECORD
