Metadata-Version: 2.1
Name: Chronix2Grid
Version: 1.2.0.post1
Summary: A python package to generate "en-masse" chronics for loads and productions (thermal, renewable)
Home-page: https://github.com/BDonnot/ChroniX2Grid
Author: Mario Jothy, Nicolas Megel, Vincent Renault, Benjamin Donnot
Author-email: mario.jothy@artelys.com
License: Mozilla Public License 2.0 (MPL 2.0)
Keywords: ML powergrid optmization RL power-systems chronics generation production load network
Platform: Windows
Platform: Linux
Platform: Mac OS-X
Platform: Unix
Classifier: Development Status :: 4 - Beta
Classifier: Programming Language :: Python :: 3.7
Classifier: Programming Language :: Python :: 3.8
Classifier: Programming Language :: Python :: 3.9
Classifier: Programming Language :: Python :: 3.10
Classifier: Programming Language :: Python :: 3.11
Classifier: License :: OSI Approved :: Mozilla Public License 2.0 (MPL 2.0)
Classifier: Intended Audience :: Developers
Classifier: Intended Audience :: Education
Classifier: Intended Audience :: Science/Research
Classifier: Natural Language :: English
License-File: LICENSE
License-File: AUTHORS.txt
Requires-Dist: click (>=7.1.1)
Requires-Dist: cufflinks (>=0.17.3)
Requires-Dist: decorator (>=4.4.2)
Requires-Dist: folium (>=0.10.1)
Requires-Dist: Grid2Op (>=1.5.2)
Requires-Dist: ipython-genutils (>=0.2.0)
Requires-Dist: ipywidgets (>=7.5.1)
Requires-Dist: json5 (>=0.9.3)
Requires-Dist: jupyter (>=1.0.0)
Requires-Dist: matplotlib (>=3.1.3)
Requires-Dist: numpy (>=1.18.3)
Requires-Dist: pandas (>=1.0.5)
Requires-Dist: pandocfilters (>=1.4.2)
Requires-Dist: plotly (>=4.5.2)
Requires-Dist: Pyomo (>=5.6.8)
Requires-Dist: pytest (>=6.2.2)
Requires-Dist: pytest-tornasync (>=0.6.0.post2)
Requires-Dist: python-dateutil (>=2.8.1)
Requires-Dist: pytz (>=2019.3)
Requires-Dist: PyUtilib (>=5.7.3)
Requires-Dist: requests (>=2.23.0)
Requires-Dist: seaborn (>=0.10.0)
Requires-Dist: scipy (>=1.4.1)
Requires-Dist: widgetsnbextension (>=3.5.1)
Requires-Dist: lightsim2grid
Requires-Dist: pypsa
Requires-Dist: cvxpy
Requires-Dist: scikit-learn
Provides-Extra: docs
Requires-Dist: numpydoc (>=0.9.2) ; extra == 'docs'
Requires-Dist: sphinx (>=2.4.4) ; extra == 'docs'
Requires-Dist: sphinx-rtd-theme (>=0.4.3) ; extra == 'docs'
Requires-Dist: sphinxcontrib-trio (>=1.1.0) ; extra == 'docs'
Requires-Dist: autodocsumm (>=0.1.13) ; extra == 'docs'
Requires-Dist: pypsa (>=0.17.0) ; extra == 'docs'
Provides-Extra: optional
Requires-Dist: ligthsim2grid ; extra == 'optional'
